example_game.py
examplepackageTeam12p3/__init__.py
examplepackageTeam12p3/__main__.py
examplepackageTeam12p3/guess_game.py
examplepackageTeam12p3-0.1.8.dist-info/LICENSE
examplepackageTeam12p3-0.1.8.dist-info/METADATA
examplepackageTeam12p3-0.1.8.dist-info/WHEEL
examplepackageTeam12p3-0.1.8.dist-info/entry_points.txt
examplepackageTeam12p3-0.1.8.dist-info/top_level.txt
examplepackageTeam12p3-0.1.8.dist-info/RECORD
